_pyfmtools.abi3.so
pyfmtools.py
pyfmtools-5.2.1.dist-info/LICENSE.txt
pyfmtools-5.2.1.dist-info/METADATA
pyfmtools-5.2.1.dist-info/WHEEL
pyfmtools-5.2.1.dist-info/top_level.txt
pyfmtools-5.2.1.dist-info/RECORD
