Metadata-Version: 2.1
Name: pyfmtools
Version: 5.2.1
Summary: Library for handling and fitting fuzzy measures
Home-page: 
Author: Gleb Beliakov, Norbert Henseler
Author-email: gleb.beliakov@deakin.edu.au, norbert.henseler@deakin.edu.au
License-File: LICENSE.txt
Requires-Dist: cffi >=1.0.0
